{"cluster_list": [{"cluster_name": "virus get pet", "representative_sentences": ["can dogs get the corona virus", "can my pets get the virus", "can pets get the viru"], "requests": ["can dogs get the corona virus", "are my pets at risk from corona virus", "can pets get the viru", "can the dog get sick with corona virus", "can pets contract the viru", "can animal get the corona virus", "can dogs get the corona virus", "can my pets carry the virus", "can my pets carry the virus", "can my pets get the virus", "can pets get the viru", "can dogs catch the corona viru", "can i get corona virus from my pet", "can animal get the corona virus", "can pets contract the viru", "can pets contract the viru", "can dogs get the coronavirus", "can dogs spread the corona virus", "can my pets get the virus"]}, {"cluster_name": "tested get test", "representative_sentences": ["can i get tested", "can i get teste", "do i need to get tested"], "requests": ["i was tested yesterday when do i hear back", "do i need to get tested", "do i need to get tested", "should we get tested if we only have symptom", "my friend has it should i t get teste", "can i test myself", "can i get teste", "ok - i've got enough of those that i think i need to get tested", "can i get tested", "should i get teste", "can i get tested", "can i test myself", "can i get tested at walgreens", "can i test myself", "can i test myself at my house", "should i get teste", "i have symptoms. where can i get tested", "can i test myself", "can i get tested", "can i get tested for cover", "should i get tested if i do not have symptoms but think i've been exposed", "can i get tested at home", "do i need to get tested", "can i get tested at my doctor's", "can i get teste", "can i get tested at home", "can i get tested", "can i get tested quickly", "can i get tested quickly", "can i get teste", "can i get teste", "i have symptoms. should i get tested", "\"i need to get test", "can i get tested for cover"]}, {"cluster_name": "spread covid others", "representative_sentences": ["how does covid sprea", "how does covid spread", "how does covid-19 spread to other"], "requests": ["how does covid spread", "how does covid sprea", "how does covid spread", "how does covid sprea", "how is the us government addressing the spread of covid-19", "how is covid-19 spread", "how does covid sprea", "how does the virus sprea", "how does covid sprea", "spreading covid to other", "spreading covid to other", "how does covid-19 sprea", "how does covid sprea", "spreading covid to other", "how does covid-19 sprea", "spreading covid to other", "how does covid-19 spread to other", "prevent the spread of the viru", "how does covid spread", "does covid spread by packages", "spreading covid to other", "how is the united states prepared for the spread of covid 19", "how is covid-19 spread", "how does covid-19 sprea", "does covid spread by packages", "prevent the spread of the viru"]}, {"cluster_name": "covid get disease", "representative_sentences": ["do i have covid", "i'm afraid i have covid-1", "is covid a disease"], "requests": ["is covid a disease", "should i get tested for covid-19", "do i have covid", "is covid dangerous to pregnant women", "i think i have covid 1", "i'm in a covid-free area can i come back to the united states", "is covid a disease", "i'm afraid i have covid-1", "is the government ready for covi", "is covid a disease", "will my head hurt if i have covid 19", "will i get paid if i have covid-19", "what is the risk of covid for pregnant women", "covid number in my state", "how would i get covid", "do i have covid", "is the covid test able to detect infection even during the incubation period", "do i have covid", "i need to be checked for covid 19", "is covid a disease", "i think i have covid 1", "do i have covid", "has the cause of covid-19 been identified", "what to do if i think i have covid", "do i have to go to the hospital if i get covi", "who is the most vulnerable to covi", "covid number in my state", "i have cancer am i at risk of coronavirus", "is covid a disease", "will i die if i get coronavirus", "does the us have a confirmed covid case", "do i have covid", "\"if i think i have covid-", "am i going to die from the covid virus", "does ma have a confirmed covid case", "should i get tested for covid-19", "is it possible to test for covid 19 during the incubation period", "i'm afraid i have covid-1"]}, {"cluster_name": "coronavirus test get", "representative_sentences": ["where can i get tested for coronavirus", "where can i get tested for coronaviru", "where can i get a coronavirus tes"], "requests": ["where can i get tested for corona", "is there a test kit for coronaviru", "i want a coronavirus tes", "testing spots for coronavirus", "is there a test kit for the coronavirus", "i want to be tested for covid-1", "i want a coronavirus tes", "where can i get tested for coronaviru", "when is the coronavirus test able to detect the disease", "who will give me my covid test results", "is there a test kit for the coronaviru", "testing spots for coronavirus", "is there test kit for coronaviru", "is there a coronavirus test ki", "where can i get a covid-19 test", "where can i go to get tested for covid", "how can i get tested for covid", "i want a test for coronaviru", "how can i get a coronavirus test", "where can i get tested for the coronavirus in new yor", "how do i get tested for covid -1", "where do i go for covid19 testing", "coronavirus test ki", "what is the test to detect covid 19", "testing spots for coronavirus", "is there a coronavirus test ki", "is there a test for teh coronaviru", "testing spots for coronavirus", "where can i get tested for coronavirus", "is there a test for the coronaviru", "how do i get a coronavirus test", "is there a test for coronaviru", "where can i get a coronavirus tes", "where should i go if i suspect i have coronavirus", "coronavirus test ki", "testing spots for coronavirus", "who do i contact if i want to get tested for covid 19 infection", "coronavirus test ki", "where can i order a coronavirus tes"]}, {"cluster_name": "quarantine quarantined long", "representative_sentences": ["do i have to quarantin", "do i have to go into quarantine", "under what circumstances do i have to quarantine"], "requests": ["how long do i have to stay in quarantine", "what if i live by myself and i'm in quarantine", "what exactly is home quarantine", "which countries are quarantine", "how can i quarantine if i have family living with me", "can i go shopping when i'm in quarantine", "under what conditions do i have to quarantine", "how do i self quarantine ", "will there be a mandated quarantin", "can someone come see me during quarantine", "do i have to quarantine when i come back from out of the country", "i came back from a country do i have to quarantine", "are quarantined visits allowed", "how can i do my job while i'm in quarantine", "are people in quarantine checked", "a colleague is breaking quarantine what should i do", "i was on vacation in another country.  do i need to quarantine", "i'm in quarantine and can't work.  what should i do", "how does quarantine work", "can i order food while in quarantine", "do i have to quarantin", "what should i do in quarantine", "how does quarantine work", "how long does it take to quarantine", "are people in quarantine checked", "is anyone checking for compliance with those ordered to quarantine", "how should i quarantine if i live with other people", "how am i supposed to be quarantined when i live with other people", "do i have to quarantin", "what can i do when i'm in quarantine", "how long will we have to self quarantine", "are quarantined visits allowed", "what if i break quarantine", "who is responsible for quarantined people", "my wife is in quarantine.  do i need to be as well", "will there be a mandated quarantin", "do i have to go into quarantine", "what should i do if i have been quarantined", "how long should i be in quarantine", "how long should you self-quarantine", "am i allowed to go to my garden in quarantine", "can i receive visits during quarantine", "how does quarantine work", "when can i be ordered to quarantine", "can i work from home during quarantine", "\"if a member of my family is in quaranti", "\"if i am in quaranti", "what if i have a roommate and i'm put under quarantine", "under what circumstances do i have to quarantine", "what countries are under a quarantine", "how long should you self-quarantine", "how long do i need to quarantine before i no longer can transmit the virus", "are quarantined visits allowed", "when do i know if i need to quarantine", "who is responsible for quarantined people", "what should i do if i live by myself and i'm in quarantine", "is anyone allowed to visit during quarantine", "what exactly is home quarantine", "how does quarantine work", "can i take a sick leave to quarantine"]}, {"cluster_name": "leave paid sick", "representative_sentences": ["do i get paid sick leav", "can i get paid sick leav", "paid sick leav"], "requests": ["what if i don't have paid sick leave", "when am i entitled to take paid sick leave", "if i get sick will i continue to get paid", "am i eligible for paid sick leav", "will paid sick leave be available for uber drivers", "will my employer give me paid leave if i have coronavirus", "what if i don't have paid sick leav", "paid sick leav", "how long can i get paid sick leav", "will i get paid leave", "paid sick leav", "will i get paid leave", "how much do i get paid for sick leav", "paid sick leav", "does my workplace offer paid sick leave", "paid sick leav", "how long can i get [paid sick leav", "do i get paid leave tim", "can i get paid sick leav", "paid sick leav", "will texas provide paid sick leav", "duration of paid sick leave", "will i get paid leave", "do i get paid leave tim", "who is able to get paid sick leav", "duration of paid sick leave", "tell me about paid sick leav", "can i still get paid sick leave for 14 days if i get coron", "paid sick leav", "can i get paid sick leav", "do i get paid sick leav", "am i eligible for sick leav", "how much paid sick leave will i get if i am contracted with the virus", "will government employees be paid during sick leave", "paid sick leav"]}, {"cluster_name": "many people infected", "representative_sentences": ["how many ppl are infected in the us", "how many people are infecte", "how many people are infected in the united state"], "requests": ["how many people are infecte", "how many cases of the virus are there in the world", "how many people are infected in the united state", "how many ppl are infected in the us", "number of infecte", "how many people are infected in illinois", "how many folks in texas are infected", "how many people total have coronavirus", "how many people are infecte", "what is the count of coronavirus infected people", "number of infecte", "number of infecte", "how many people are infected with corona virus currently in texas", "are people infected in my city ", "how many people are sick throughout the world", "how many people total have coronavirus", "how many people have the virus in our count", "how many coronavirus cases are there in my area", "how many people are infecte", "how many people in texas have corona virus", "how many people have the virus", "number of infecte", "how many people ar sick in the us"]}, {"cluster_name": "school closed kid", "representative_sentences": ["are schools close", "are schools closed ", "are my schools close"], "requests": ["is my school closed", "is my kids school close", "is the school close", "are schools closed ", "are my schools closed", "is my kids school close", "they closed my school and i have nowhere to work", "are schools closed in my are", "are schools closed ", "are my children's schools closed", "are schools closed ", "what schools are close", "is my kids school closed", "are schools in my area close", "is my kids school close", "are my schools close", "is the school close", "are schools closed", "is my kids school closed", "what schools are close", "which schools are closed", "are my schools closed", "which schools are closed", "are my schools closed", "are my schools closed", "are my schools closed", "what schools are close", "is the school close", "are schools close", "is my school close", "are schools shut down", "are schools shut down", "what schools are close", "are schools in my area close", "are schools closed", "is my school closed", "what schools are close", "is my kids school closed", "which schools are closed", "are schools closed "]}, {"cluster_name": "flu coronavirus v", "representative_sentences": ["what's the difference between flu and coronavirus", "how's the flu different from coronavirus", "flu vs coronaviru"], "requests": ["flu vs covid1", "what's the difference between the flu and coronaviru", "flu vs. covid-1", "flu vs. covid-1", "is the coronavirus the same as sars", "what's the difference between flu and coronavirus", "flu vs coronaviru", "sars vs corona virus", "flu vs covid1", "how is corona virus different than sars", "sars vs corona virus", "how is flu different from corpnaviru", "flu vs coronaviru", "how's the flu different from coronavirus", "flu vs. covid-1", "flu vs coronaviru", "how do flu symptoms differ from coronavirus symptoms", "how's the flu different from coronavirus", "what is different between flu and coronaviru", "flu vs coronaviru", "sars vs corona virus", "how is the flue different from the coronavirus", "sars vs corona virus", "flu vs. covid-1", "is the coronavirus the same as a cold", "sars vs corona virus", "how is flu different from corpnaviru", "is this the same as the flu", "what is the difference between flu and coronaviru", "what is the difference between the flu and coronaviru", "what is the difference between covid-19 and the fl", "what's the difference between flu and coronaviru", "is covid the same as the flu"]}, {"cluster_name": "symptom common illness", "representative_sentences": ["what are the symptom", "what are symptoms", "what are the symptoms"], "requests": ["what are symptom", "what are my symptom", "what are the symptoms", "what are symptoms", "what are the symptom", "what are my symptom", "what are symptoms", "what are the common symptom", "what are symptom", "what are my symptom", "i have illness symptom", "hi what are the symptoms", "what are the symptoms", "what are symptom", "what are the symptom", "what is the first sympto", "tell me about the symptom", "what are the types of symptom", "what are symptom", "i have illness symptom", "what are symptom", "what are the common symptom", "what are the symptoms", "what symptoms are typical with this diseas", "what are the symptom", "what are the symptoms of the disease", "what are the symptoms", "what are the symptom", "what are symptoms", "what are the common symptom", "what are the symptoms", "i have illness symptom", "i thing i feel symptoms of the diseas", "what are the symptom", "tell me about the symptom", "what are symptoms", "what are the symptoms i should look out fo", "what are symptoms", "what are my symptom"]}, {"cluster_name": "hate like", "representative_sentences": ["i hate thi", "i don't like thi", "i hate yo"], "requests": ["i hate thi", "i hate thi", "i hate thi", "i don't like thi", "i hate thi", "i don't like thi", "i don't like thi", "i don't like thi", "i hate thi", "i hate thi", "i hate thi", "i don't like thi", "i hate yo"]}, {"cluster_name": "covid get transmitted", "representative_sentences": ["how is covid transmitted", "is covid transmissible from animals", "can pets get covi"], "requests": ["can pets get covi", "how is covid transmitted", "can dogs get covid19", "can dogs get covid19", "how is covid transmitted", "is covid transmissible from animals", "how can covid be transmitte", "can dogs get covid19", "can dogs get covid19", "can pets get covi", "can pets get covi", "how can covid be transmitte", "how is covid transmitted", "how can covid be transmitte", "can pets get covi", "is covid transmissible from animals", "how is covid transmitted", "how is covid transmitted"]}, {"cluster_name": "covid treat prevention", "representative_sentences": ["how to prevent covid infection", "what is effective prevention against covid", "what will help me prevent covid infection"], "requests": ["how to avoid catching covid-19", "how to treat covid", "what is effective prevention against covid", "how to treat covid", "what is the best prevention", "how to treat covid", "how to prevent covid infection", "how do i avoid covid-19", "what are some good tips for prevention", "what is the best prevention", "what is the treatment for covid-19", "how to prevent the spread of the viru", "what rules should i follow to prevent covid illness", "what will help me prevent covid infection", "in the event there is a large number of infected and hospitals can't manage to treat everyone what is recommended treatment for home quarantine and self-medication", "how to treat covid", "how to avoid catching covid-19", "what is the most effective prevention", "what is effective prevention against covid", "what is the most effective prevention", "how to treat covid", "how do we treat covid"]}, {"cluster_name": "No name", "representative_sentences": ["who you are", "who are yo"], "requests": ["who you are", "who you are", "who you are", "who are yo", "who you are", "who are yo", "who you are", "who you are", "who you are", "who are yo", "who are yo"]}, {"cluster_name": "school back kid", "representative_sentences": ["when can my kids go back to schoo", "when can kid go back to schoo", "when can my kid go back to schoo"], "requests": ["when can my high school senior go back to schoo", "when do the children go back to schoo", "when can i return to school", "when can i return to school", "when can kid go back to schoo", "when will my good go back to school", "where can my kids go back to schoo", "can my kids return to high schoo", "when can i send my kids back to schoo", "when can my kids back schoo", "when can my kids go back to high school in 7871", "when is school back in session", "can my child go to school", "when can kids return to schoo", "when can my kids go back to schoo", "when will my kids be back in school", "when can my kids go back to college", "when can my kid go back to colleg", "when can my kid go back to schoo", "when can my kid go back schoo", "when can my kid go back to high schoo"]}, {"cluster_name": "vaccine covid cure", "representative_sentences": ["is there a vaccine for covid-19", "is there a covid vaccine", "is there a vaccine for covid-1"], "requests": ["is the covid vaccine ready", "is there a vaccine for thi", "is there a vaccine for coronavirus", "is there a vaccine for corona viru", "is there a vaccine for covid-1", "is there a vaccine for coronavirus", "are there disinfectants available that can inactivate (kill) covid-19", "is there a vaccine for covid-19", "is there a vaccine", "is there a vaccine for covi", "is the covid vaccine ready", "is there a covid vaccine", "is there a vaccine for the coronavirus", "is there a cure for covid-19", "is there a cure for covid-19", "is there a cure for covid 19", "is there a vaccine for covid-1", "is there a vaccine for covid-19"]}, {"cluster_name": "park open local", "representative_sentences": ["are the local parks open", "what parks are open", "what city parks are open"], "requests": ["are the national parks closed", "what city parks are open", "are the local parks open", "are the local parks open", "what parks are open", "are the national parks closed", "are the national parks closed", "what city parks are open", "what parks are open", "will the parks and bike trails remain open", "are the local parks open"]}, {"cluster_name": "long last coronavirus", "representative_sentences": ["how long does the coronavirus last", "how long does the corona virus last", "how long does the virus last"], "requests": ["how long does the virus las", "incubation period of coronavirus", "how long does the coronavirus last", "how long does the disease last", "incubation period of coronavirus", "how long does coronavirus las", "incubation period of coronavirus", "how long does the virus last", "how long does the coronavirus last", "how long are people infected with covid-19 before they are symptomatic", "what is the incubation period of covid", "what is the mortality rate of the virus", "how long does the disease last", "incubation period of coronavirus", "how long is the incubation period for covid-1", "how long does the virus las", "how long does covid-19 last", "how long is the incubation period of covid 19", "incubation period of coronavirus", "how long does coronavirus las", "how long does the virus last", "how long does the corona virus last"]}, {"cluster_name": "unemployment apply benefit", "representative_sentences": ["how can i apply for unemployment", "how do i apply for unemploymen", "how to i apply for unemploymen"], "requests": ["i can't go to work.  can i get unemployment", "how to apply for unemploymen", "how to apply for unemploymen", "i have a question about unemploymen", "how do i apply for unemploymen", "apply for unemploymen", "what do i do if i don't have unemployment insurance", "i need to apply for unemployment.  how do i do i", "apply for unemploymen", "how do i apply for unemployment because of coid-1", "how to i apply for unemploymen", "how do i apply for unemploymen", "how long can i get unemployment", "apply for unemploymen", "where can i apply for unemploymen", "where can i apply for unemploymen", "how can i apply for unemployment", "how do i apply for unemployment benefits", "i have a question about unemploymen", "how can i apply for unemployment during this outbreak", "how do i apply for unemployment benefits due to covid-19", "how to i apply for unemploymen"]}, {"cluster_name": "symptom covid coronvirus", "representative_sentences": ["what are the covid-19 symptoms", "what are the symptoms of covid-1", "what are the early symptoms of covid-19"], "requests": ["what are the covid symtom", "what are covid 19 symptom", "what are the first symptoms for covid", "what are the symptoms of covid-1", "what are the symptoms of coronoaviru", "is rash a symptom of covid-19", "is rash a symptom of covid-19", "what are covid 19 symptom", "what are the symptoms of covid", "what are the symptoms of coronaviru", "what are the covid-19 symptoms", "what are symptoms of coronviru", "what are the covid-19 symptoms", "what are the covid-19 symptoms", "my girlfriend has symptoms of covid-1", "what is the risk of my child becoming sick with covid-19", "what are the symptoms of covid", "what are symptoms of coronviru", "what are the most common symptoms of covid", "what are symptoms of coronviru", "my girlfriend has symptoms of covid-1", "what are the early symptoms of covid-19", "how do i know if i'm sick with covid-19", "is a headache a symptom of the coronavirus"]}, {"cluster_name": "respirator wear like", "representative_sentences": ["should i buy a respirator", "do i have to wear a respirator", "should i wear a respirator"], "requests": ["i'd like a respirato", "i'd like a respirato", "why are there no masks and respirators in pharmacies", "i often travel by public transport. should i wear a respirator", "will a respirator help me", "will a respirator help me", "i'd like a respirato", "do i have to wear a respirator", "why aren't there respirators", "can i go out without a respirator", "should i wear a mask or a respirator", "i'd like a respirato", "should i wear a respirator", "why aren't there respirators", "should i wear a respirator", "when should i wear a respirator", "why aren't there respirators", "i'd like a respirato", "will a respirator help me", "why aren't there respirators", "why aren't there enough masks and respirators", "should i buy a respirator", "should i wear a respirator", "why aren't there respirators"]}, {"cluster_name": "throat sore ihave", "representative_sentences": ["i have sore throa", "i have a sore throa", "ihave sore throa"], "requests": ["i have sore throa", "my throat hurts and i have a headache as wel", "i have a sore throa", "i have a sore throa", "ihave sore throa", "my throat and head hur", "ihave sore throa", "i have a sore throa", "i have headache and sore throat ..what should i do ", "ihave sore throa", "ihave sore throa", "\"i have sore thro"]}, {"cluster_name": "coronavirus prevent medicine", "representative_sentences": ["how do i treat coronavirus", "what\u2019s the best way to prevent coronavirus", "how do i avoid coronaviru"], "requests": ["how can i lower my temperature if i have the coronavirus", "what is recommended by who and other international organizations regarding coronavirus", "how can i protect my family from the spread of coronavirus", "how can i prevent coronaviru", "what\u2019s the best way to prevent coronavirus", "how do i avoid coronaviru", "what medicines should i take if i have coronaviru", "what cleaning methods kill the coronavirus", "what is the best way to prevent coronaviru", "what medicine should i avoid taking if i have coronaviru", "what medicine should i take for covid 1", "how do i avoid coronaviru", "what cleaning methods kill the coronavirus", "medication that helps with coronaviru", "what can i do to prevent getting coronavirus", "how do i avoid coronaviru", "how do i treat coronavirus", "what medicine should i be taking for covid 1", "how can i prevent coronaviru", "i heard about a medication for coronavirus treatmen", "medication that helps with coronaviru"]}, {"cluster_name": "school open college", "representative_sentences": ["are schools open", "are schools ope", "when will the schools open"], "requests": ["are schools open", "are schools open", "are schools ope", "when will schools close", "when will my kids school reope", "are schools ope", "are schools ope", "are schools ope", "are colleges ope", "are schools ope", "are schools ope", "are colleges ope", "are schools open", "are colleges ope", "when will the schools open", "i live in 78709. when will my kids high school reopen", "are schools open", "when will my kids school reope", "are colleges ope", "are schools open", "are schools ope", "when will schools close", "when will the schools open", "when will the schools open"]}, {"cluster_name": "get test tested", "representative_sentences": ["where do i get a tes", "where can i get a tes", "where can i tes"], "requests": ["none of those sound like they cover how to get tested. can you tell me how/where i can get tested", "where can i get tested in houston", "where can i get tested in new mexic", "how do i get tested", "where cani get teste", "how do you tes", "where can i tes", "how do you tes", "where can i get a test", "where can i be teste", "where i can get teste", "how can i get teste", "where cani get teste", "how can i get my test results", "how do you tes", "where can i get a test don", "where can i get a test ki", "where cani get teste", "where can i get tested for cover-1", "how do i get a test", "where can i tes", "where can i get a tes", "where cani get teste", "how can i get teste", "where do i get a tes", "where can i get tested", "how can i get a tes", "where can i get a test", "where can i tes", "how do you tes", "how can i get teste", "where i can get teste", "where can i get a tes", "i am in new york where should i get teste", "how do i get a test", "where do i get a tes", "where can i get tested in alabam", "how do you tes", "can you direct me to the nearest test cente", "where can i tes", "where can i get a test done"]}, {"cluster_name": "covid die rate", "representative_sentences": ["what is the mortality rate of covid-19", "what is the mortality rate of covid-1", "what has the world health organization said about covid 19"], "requests": ["which countries are affected by covid 19", "what is the mortality rate of covid-1", "can i die from covid-1", "will i die from covid-1", "what measures is the us taking against covid-19", "how many cases of covid-19 are in the us", "how many people have covid-19 in the whole world", "what is the mortality rate for covid 1", "will i die from covid-1", "where can i find information about covid 19 for the world", "when will covid-19 medicines be ready", "can i die from covid-1", "which countries has covid-19 been detected in", "where can i find more information about covid 19", "which age group is at an increased risk of getting covid 19", "will i die from covid-1", "what has the world health organization said about covid 19", "what is the hospital capacity for covid 19 patients", "is the us well prepared for covid 1", "when will covid-19 medicines be ready", "what is the mortality rate of covid-19"]}, {"cluster_name": "coronavirus corona virus", "representative_sentences": ["what is the corona virus", "what is corona virus", "what is the coronavirus"], "requests": ["how has coronavirus spread around the world", "what is the coronavirus", "does alcohol kill the coronavirus", "what'is corona viru", "how does coronavirus spread", "what is corona virus", "what is corona viru", "what is the corona viru", "what is corona viru", "what is the coronavirus", "what'is corona viru", "what is the coronavirus", "what is the corona virus", "what is the coronavirus", "origin of coronaviru", "what is corona virus", "what is corona viru", "what is the corona virus", "origin of coronaviru", "how does coronavirus spread", "what is the corona viru", "what is novel coronavirus", "what is corona viru", "does the sun kill coronavirus", "is the coronavirus the same as mers", "what is corona viru", "origin of coronaviru", "origin of coronaviru", "where did corona virus start from", "does alcohol kill the coronavirus", "origin of coronaviru", "what'is corona viru", "origin of coronaviru", "does the sun kill coronavirus", "where did corona virus start from", "what is the risk of coronavirus for pregnant women", "where did the coronavirus come from", "does alcohol kill the coronavirus"]}, {"cluster_name": "contagious coronavirus become", "representative_sentences": ["is covid-19 contagious", "is covid19 contagious", "how contagious is covid-19"], "requests": ["is covid19 contagious", "is covid-19 contagious", "how contagious is covid-19", "is covid19 contagious", "is covid-19 contagious", "is covid19 contagious", "is coronavirus contagious", "when does a person become contagious", "is covid-19 contagious", "is coronavirus contagious", "is covid-19 contagious", "is covid19 contagious", "how contagious is covid-19", "is coronavirus contagious", "how contagious is covid-19", "is it contagiou", "is covid19 contagious", "is covid19 contagious"]}, {"cluster_name": "covid come heard", "representative_sentences": ["what is covid-19", "what is covid-19", "what is covid"], "requests": ["what is covi", "what is covid1", "what is covid-1", "what is covid1", "what does covid stand for", "where did covid come from", "what is covid", "what is covid-1", "what is covid-19", "what is covid-19", "i heard about covid what is it", "what is covid", "what is covid-1", "what is covid", "where did covid come from", "what is covid-1", "what is covid1", "what is covid1", "covid what is i", "what is covid", "what is covid1", "what is covid-19", "what is covi", "where can i learn more about covid", "what is covid-19", "what is covid-19", "what is covid", "what is covi", "what is covid-1", "what is covid-19", "what is covid-19", "what is covid-19", "what is covid-1", "what is covid", "what is covid", "where did covid come from", "what is covi"]}, {"cluster_name": "outside go safe", "representative_sentences": ["can i go outside", "can i go outsid", "is it safe to go outside"], "requests": ["when can i go outsid", "am i safe outside", "is it safe to go outside", "am i safe outside", "is it dangerous to go outside", "can i go for a run outside", "can i go outsid", "is it dangerous to go outside", "can i go outside", "can i go outsid", "am i safe outside", "can i go outside", "can i go outsid"]}, {"cluster_name": "mask available get", "representative_sentences": ["where can i get masks", "when can i buy a mask", "when will masks be available"], "requests": ["when can i buy a mask", "when will respirators and masks be finally sold", "when will masks be available", "why can't i get or find a mask or a respirator anywhere", "why are no masks or respirators available anywhere", "when will masks be available at retail stores? they are not yet and we can get infected on public transport before they are", "can a mask help me", "where can i get masks", "why aren't any masks available", "where do people get protective masks or disinfectants", "when can i buy a mask", "when can i buy a mask at a pharmacy", "why aren't any masks available", "can a mask help me", "when should i wear a mask", "can a mask help me", "when will masks be available", "where can i get masks"]}, {"cluster_name": "infected think get", "representative_sentences": ["how can i get infected", "i think i'm infecte", "how can one know if they have been infected"], "requests": ["how can one know if they have been infected", "how can i get infected", "i think i'm infecte", "i think i'm infecte", "how does the infection sprea", "how can i get infected", "i think i'm infecte", "is it possible to get infected from the infected person the next day", "i think i'm infecte", "how can i get infected", "how does the infection sprea", "i think i'm infecte", "\"if infect"]}, {"cluster_name": "store go grocery", "representative_sentences": ["can i go to the grocery stor", "can i go to the grocery store", "can i go to grocery store"], "requests": ["can we go to the store", "can i go to grocery store", "can i go to the store", "can we go to the store", "can i go to the grocery store", "are grocery stores still ope", "are grocery stores still ope", "is it okay to go grocery shopping", "is it safe to go to the grocery store", "can i go to the store", "can i go to the grocery stor", "am i allowed to go to the grocery store", "can i go to grocery store", "can i still go to the grocery store", "are grocery stores still ope", "can i still go grocery shoppin", "is it ok for me to go to the grocery stor"]}, {"cluster_name": "abroad returning return", "representative_sentences": ["returning from abroa", "can i return to the united states if i am abroad", "can i return to the united states"], "requests": ["can i return to the united states", "returning from abroa", "i am in europe and i want to return to the united states. is that possible", "returning from abroa", "can i return to the united states if i am abroad", "returning from abroa", "returning from abroa", "returning from abroa", "returning from abroa", "when can i return to the united states"]}], "unclustered": ["\"i live in ontario", "\"i have a fever", "i have a fever. should i go to the hospital?\n", "i have a fever\n", "should i go to the hospital\n", "i feel congested and have a fever\n", "i have a fever\n", "what medicines work best\n", "what medicines work best\n", "what medicines work best\n", "what medicine work best for treatment ?\n", "what kind of medicine should i take\n", "should i see a doctor if i am showing the symptoms?\n", "should i go to the doctor now\n", "who should i call if i have symptoms?\n", "i want to be transferred\n", "i want to be transferred\n", "i want to be transferred\n", "is it safe to fly to seattle?\n", "how are you\n", "how are you\n", "how are you doing\n", "how are you\n", "how is it going\n", "how are you\n", "how is it going\n", "how are you\n", "should i quit the study abroad program?\n", "what can i ask you\n", "what can i ask you\n", "who to contact when i'm in the high risk area\n", "how can i get screened\n", "where can i get screened?\n", "how do i get screened?\n", "how do i get screened?\n", "where can i get screened?\n", "how do i get screened?\n", "where can i get screened?\n", "where should i go to get screened\n", "how can i get screened\n", "i can not breath very well\n", "daughter is studying abroad what do we do?\n", "should i take theraflu?\n", "should i take theraflu?\n", "should i take theraflu?\n", "what does a pandemic mean?\n", "the who has declared a pandemic in the world. what does this mean?\n", "what is a pandemic?\n", "how is a pandemic different from an epidemic?\n", "what is a pandemic?\n", "what does a pandemic mean?\n", "what does a pandemic mean?\n", "i want to talk to an agent\n", "i want to help with babysitting.\n", "i want to help with babysitting.\n", "should i spray myself or my kids with disinfectant?\n", "i want to help those at high risk with shopping. where can i find information on how to help?\n", "what can i do if i lose my job?\n", "what can i do if i lose my job\n", "what happens if i lose my job?\n", "i need help\n", "i need help\n", "i need help\n", "i need help\n", "i need help\n", "i need help\n", "i need help\n", "how dangerous is this?\n", "how dangerous is this?\n", "which countries are high risk to travel to?\n", "show me the list of high-risk countries.\n", "which countries are more of a risk?\n", "what are the risky countries?\n", "which countries should i avoid?\n", "what are the risky countries?\n", "which countries should i avoid?\n", "should i go to the er if i have a cough\n", "i have an irritating cough\n", "i am coughing.  should i call my doctor?\n", "should i get tested if i have a cough?\n", "everything is horrible\n", "everything is horrible\n", "everything is horrible\n", "everything is horrible\n", "everything is horrible\n", "are there any cases near me\n", "where are cases?\n", "where are cases?\n", "where are cases?\n", "where are cases?\n", "are there any cases near me\n", "where are cases?\n", "where are cases?\n", "should i feel safe going to the movies?\n", "who is in danger\n", "who is in danger\n", "what groups are most at risk\n", "who is most at risk\n", "who is most at risk?\n", "what population groups are most at risk?\n", "what groups are most at risk\n", "who is most at risk?\n", "who is most at risk?\n", "is hs 123 open?\n", "is hs 123 open?\n", "is hs 123 open?\n", "is hs 123 open?\n", "what opinion does the world health organization (who) have on next steps?\n", "are events being shut down?\n", "are events being shut down?\n", "why is the government shutting down my event?\n", "is this worse than flu\n", "is this worse than flu\n", "is this worse than the flu?\n", "is this worse than flue\n", "is this worse than the flu?\n", "is this worse than flue\n", "is this worse than flue\n", "how many patients are infected with cornona virus in collin county\n", "washing your hands effectively\n", "how often should i wash my hands?\n", "washing your hands effectively\n", "washing your hands effectively\n", "washing your hands effectively\n", "how to wash your hands properly?\n", "how should i properly wash my hands?\n", "how do i wash my hands properly?\n", "i am a teacher / educator / employee of a school what restrictions apply to me?\n", "how long does it last\n", "how long does it last?\n", "how long does it last\n", "how long does it last\n", "\"i live in an apartment with my girlfriend", "should i cancel my flight to denver?\n", "i'm hanging up\n", "i'm hanging up\n", "i'm hanging up\n", "i'm hanging up\n", "i'm hanging up\n", "i'm hanging up\n", "will i throw up if i have the virus?\n", "will i poop a lot if i have the virus?\n", "yes it is\n", "yes it is\n", "yes it is\n", "yes it is\n", "yes it is\n", "yes it is\n", "can i travel?\n", "can i travel?\n", "can i travel for work?\n", "can i travel for work?\n", "can i travel?\n", "can i travel out of the country?\n", "can i travel?\n", "i want to talk to someone.\n", "i want to talk to a person.\n", "i want to talk to someone.\n", "am i going to die?\n", "am i going to die\n", "what cleaning regimen should i follow\n", "effective cleaning and hand washing techqniques\n", "are my kids going to die?\n", "are my kids going to die?\n", "will students still graduate this year?\n", "is graduation delayed?\n", "is graduation delayed?\n", "is graduation delayed?\n", "will graduations be pushed back?\n", "will graduations be pushed back?\n", "is graduation delayed?\n", "is graduation delayed?\n", "is graduation delayed?\n", "is there a medication to reduce temperature with covid-19?\n", "can medication be used to reduce fever?\n", "can medication reduce fever caused by a possible covid infection?\n", "this is hateful\n", "this is hateful\n", "this is hateful\n", "this is hateful\n", "is anyone near me sick\n", "am i sick\n", "am i sick\n", "when does covid vacation end?\n", "when does covid vacation end?\n", "when does covid vacation end?\n", "what happens after the ordered three-week closure period ends?\n", "this is crap\n", "this is crap\n", "this is crap\n", "this is crap\n", "this is crap\n", "this is crap\n", "this is crap\n", "i traveled to italy recently. what do i do?\n", "i just travelled. what do i do?\n", "switch me to an operator\n", "switch me to an operator\n", "i want to switch to an operator.\n", "do i need lysol wipes?\n", "do i need lysol wipes?\n", "do i need lysol wipes?\n", "how does this work\n", "\"i need to get home from abroad", "can the government close public places?\n", "can the government close public places?\n", "is the government legally allowed to close shops and restaurants?\n", "i'm having respiratory problems\n", "i'm having respiratory problems\n", "will classes be moved to summer?\n", "will classes be moved to summer?\n", "will there be school in the summer?\n", "will there be exams in the summer?\n", "what is the maximum number of people allowed to meet right now?\n", "are groups of people allowed to meet?\n", "\"if i have syptoms", "how long before i get symptons?\n", "how long before i get symptons?\n", "how long do symptons take to develop ?\n", "how long before i experience covid-19 symptons?\n", "how do i ensure my family is safe?\n", "what should i do to stay safe?\n", "how do i stay safe\n", "what can i do to stay safe\n", "how do i protect myself?\n", "how do i stay safe\n", "how do i stay safe\n", "how can i get the latest news on my school closure?\n", "when will the nhl return?\n", "when will the nhl return?\n", "when will the nhl return?\n", "i have travled recently. what do i do?\n", "how does cover-19 compare to the sars epidemic?\n", "i suspect i have the virus who can i call?\n", "how do i catch the virus?\n", "what should i do to contain the spread of the virus\n", "how do i catch the virus?\n", "what can you do\n", "what can you do\n", "what can you do\n", "what can you do\n", "does eating garlic help?\n", "does eating garlic help?\n", "does eating garlic help?\n", "does eating garlic help?\n", "does eating garlic help?\n", "can i leave for an exchange trip?\n", "when will the ncaa championships be held?\n", "how does the state of emergency affect me?\n", "how long will the state of emergency last?\n", "events and large gatherings\n", "events and large gatherings\n", "events and large gatherings\n", "events and large gatherings\n", "events and large gatherings\n", "can i get infected if i receive a package\n", "can i get infected through a package from china\n", "is it possible to get infected with coronavirus if i have my goods shipped from chinese stores?\n", "\"all the stores are out of disinfecting wipes", "\"i live in austin", "how many hospital beds are available in the united states?\n", "how many hospital beds do we have in the us?\n", "how many beds are available in the hospitals?\n", "how many beds are available for covid-19 patients?\n", "what does breathlessness look like\n", "what does breathlessness look like\n", "what does breathlessness look like\n", "how do i know if my concert is cancelled?\n", "i have a burning feeling in my chest\n", "connect me to someone\n", "connect me to someone\n", "connect me to someone\n", "connect me to someone\n", "can i still attend a conference\n", "can i still attend a conference\n", "should i make an appointment with my dr?\n", "when should i call a doctor\n", "what should i do\n", "i do not know what to do\n", "what should i do\n", "what should i do\n", "what position does the who have?\n", "what position does the who have?\n", "how do i know if im sick\n", "when should i go to the hospital?\n", "when should i go to the doctor?\n", "when should i go to a doctor?\n", "can i go to the hospital?\n", "what should i do if the hospital won't take me in?\n", "can i go to the hospital?\n", "i'm a medical student and i want to get involved. how can i help?\n", "my child has a high fever and is coughing. what should i do?\n", "my child is coughing. should i be worried?\n", "what are the crisis measures currently in place?\n", "how can i avoid getting sick?\n", "what can i do to avoid getting sick?\n", "how to i prevent myself from getting sick?\n", "how can i not get sick\n", "what should i do to avoid getting sick?\n", "what can i do to not get sick?\n", "i want to consult an expert.\n", "what are symtoms?\n", "what are symtoms?\n", "how many people have contracted the virus in pennysylvania\n", "can i lower my temperature using medication?\n", "are there any travel restrictions in place yet?\n", "can i work from home?\n", "tell me about working from home?\n", "am i able to work from my home office?\n", "can i work from home?\n", "can i work from home?\n", "my doctor hasn't given me my test results back yet.\n", "describe shortness of breath\n", "what is shortness of breath\n", "how do i know if i'm suffering from shortness of breath\n", "what is shortness of breath\n", "describe shortness of breath\n", "how long does it take for the virus to run through my system?\n", "has anyone died of coronavirus in my state?\n", "who am i talking to\n", "who am i talking to\n", "how will the shutdown impact my child's attendance records?\n", "what can you help me with\n", "should i avoid people?\n", "should i avoid people?\n", "my eyes are burning\n", "my eyes are burning\n", "my eyes are burning\n", "my eyes are burning\n", "can i go to park\n", "how long will it be until there is a vaccine?\n", "how long does it take to develop a vaccine?\n", "is it possible to estimate how long it will take to administer the drug / vaccine to people?\n", "how do i know if i have this thing\n", "how do i know if i got this thing\n", "how do i know if i got this\n", "can i visit relatives in another state?\n", "i want to help with shopping for the old.\n", "what grocery store in keller is open?\n", "what does a state of emergency mean?\n", "a national emergency was declared in the united states. what does this mean?\n", "what is a national emergency?\n", "how long has the national emergency been in place?\n", "we're on an exchange trip now what?\n", "\"i am on a exchange trip", "i am abroad who to contact?\n", "i am abroad who to contact?\n", "i am abroad who should i contact?\n", "i am currently traveling out of the country. who should i contact?\n", "how would i catch it?\n", "i'm afraid and don't know what to do\n", "can i take ibuprofen if i have corona virus?\n", "i'm teaching at a school that's closed. what should i do?\n", "i'm working at a school that's closed now. what should i do?\n", "how many current cases are there in illinois\n", "is there a medication that can help me feel better?\n", "i need medicine. can i go to the store?\n", "how do you protect yourself?\n", "how do you protect yourself?\n", "how long is teaching on hold?\n", "is it even possible to avoid the virus?\n", "what is a safe distance when someone brings me groceries?\n", "my husband has coronavirus symptoms\n", "my husband has coronavirus symptoms\n", "\"i'm coughing", "\"i have a cough but am breathing fine", "can i protect myself by drinking alcohol\n", "i want to help i'm a student.\n", "what happens when the hospital is full?\n", "the hospital is full and they sent me home.\n", "i think i might have the virus.\n", "hello are you a living person?\n", "its been a week. who can i call to get my test results?\n", "when can i get my results?\n", "when can i get my results?\n", "what has our government already done to reduce the risk of spreading the disease\n", "how long will i feel terrible?\n", "how long will i feel terrible?\n", "is it safe to go to costco?\n", "what can i do to prevent coivd?\n", "how do i know whether to go to the doctor?\n", "go to hell\n", "i'm a doctor how can i help?\n", "how often do i need to clean my home to prevent the spread of coronavirus?\n", "how to distinguish it from a common cold.\n", "what does the who do?\n", "what does the who do?\n", "do i need to do both?\n", "can i go to the grocery store or will i catch corona\n", "what should i do if i am a teacher?\n", "is it possible to detect the disease during the incubation period?\n", "can you help me?\n", "can you help me?\n", "how long do i have to be stuck at home?\n", "should i change my travel plans?\n", "what is the treatment for this disease?\n", "what measurements is the government taking?\n", "the son is on an exchange trip\n", "is there a nationwide curfew?\n", "does a mask or respirator help prevent covid infection?\n", "what if i urgently need to take a flight?\n", "can my friends visit me?\n", "can my friends visit me?\n", "how long is the incubation period?\n", "when will the national emergency end?\n", "when will the national emergency end?\n", "how many people in the world have died?\n", "when did i need to call the doctor?\n", "when do i call a doctor\n", "do i need a doctor's note to travel?\n", "will i get a refund for a ticket i purchased?\n", "if i have covid how long do i have to self isoclate\n", "can i travel in the current emergency situation?\n", "do i have to wear a mask when i'm outside or taking a walk?\n", "should i wear a mask so i don't get infected?\n", "do i need to wear a face mask?\n", "when should i wear a mask?\n", "which countries have been affected?\n", "how do i know if i have this issue\n", "do my test results come in the mail?\n", "best vitamin to take\n", "what does the ordered school closure mean for report cards?\n", "do i need to stay home\n", "do i need to disinfect my cell phone when i get home\n", "how long does it take to get unemployment\n", "how do i prevent catching the desease\n", "how do i clean my home properly?\n", "what cleaning regimen should i follow\n", "how long do i have to self isolate if i have tested positive?\n", "when will teaching go back to work?\n", "do we have enough protective measures?\n", "if i only have a sore throat is it coronavirus?\n", "i have a temperature and cough. do i have the coronavirus?\n", "is lysol enough to get rid of covid virus from countertops\n", "how is it possible that the state does not have enough masks and respirators?\n", "are you a robot?\n", "what should i do when i get back from another country?\n", "what should i do if i returned from another country?\n", "what if i live alone and can't go out to buy food?\n", "is it dangerous for postal workers\n", "the hospital sent me home because of a lack of beds.\n", "how long can i expect to be sick?\n", "how do i get rid of germs at my home\n", "i would like to get involved as a volunteer in the current situation but i do not know how to get involved.\n", "do i have to use bleach to kill coronavirus?\n", "how long should i quarrantine?\n", "i hate these kinds of things\n", "should my child stay home from school?\n", "can i go to the gym or should i avoid it?\n", "how many cases are there in texas?\n", "does the virus spread thru surfaces\n", "whats the difference between cleaning and disinfecting?\n", "what sports are being cancelled?\n", "when can i expect drugs for the virus?\n", "who is eligible to get paid sick leave\n"]}